pvrhinodemo/rhino_demo_file.py
pvrhinodemo/rhino_demo_mic.py
pvrhinodemo-4.0.1.dist-info/METADATA
pvrhinodemo-4.0.1.dist-info/WHEEL
pvrhinodemo-4.0.1.dist-info/entry_points.txt
pvrhinodemo-4.0.1.dist-info/top_level.txt
pvrhinodemo-4.0.1.dist-info/RECORD
