Metadata-Version: 2.1
Name: pvrhinodemo
Version: 4.0.1
Summary: Rhino Speech-to-Intent engine demos.
Home-page: https://github.com/Picovoice/rhino
Author: Picovoice
Author-email: hello@picovoice.ai
Keywords: Speech-to-Intent,voice commands,voice control,speech recognition,natural language understanding
Classifier: Development Status :: 5 - Production/Stable
Classifier: Intended Audience :: Developers
Classifier: License :: OSI Approved :: Apache Software License
Classifier: Operating System :: OS Independent
Classifier: Programming Language :: Python :: 3
Classifier: Topic :: Multimedia :: Sound/Audio :: Speech
Requires-Python: >=3.9
Requires-Dist: pvrhino==4.0.1
Requires-Dist: pvrecorder==1.2.7
